jsepp/__init__.py
jsepp/config.py
jsepp/data.py
jsepp/dbutils.py
jsepp/ml.py
jsepp/tools.py
jsepp/visualize.py
jsepp/water.py
jsepp-0.1.10.dist-info/METADATA
jsepp-0.1.10.dist-info/WHEEL
jsepp-0.1.10.dist-info/top_level.txt
jsepp-0.1.10.dist-info/RECORD
