Metadata-Version: 2.1
Name: jsepp
Version: 0.1.10
Summary: a package for general environmental data processing
Author: Hansen Zhao
Author-email: zhaohs12@163.com
Requires-Dist: pymysql
Requires-Dist: pymongo
Requires-Dist: numpy
Requires-Dist: pandas
Requires-Dist: openpyxl
Requires-Dist: scipy
Requires-Dist: statsmodels
Requires-Dist: haversine
